wisefish/__init__.py
wisefish/cli.py
wisefish/default_config.json
wisefish-0.1.0.dist-info/METADATA
wisefish-0.1.0.dist-info/WHEEL
wisefish-0.1.0.dist-info/entry_points.txt
wisefish-0.1.0.dist-info/top_level.txt
wisefish-0.1.0.dist-info/RECORD
