Metadata-Version: 2.4
Name: wisefish
Version: 0.1.0
Requires-Python: >=3.8
Requires-Dist: platformdirs>=3.0
Dynamic: requires-dist
Dynamic: requires-python
